[
  {
    "name": {
      "vi": "Vẽ và Đoán",
      "en": "Draw and Guess"
    },
    "desc": {
      "vi": "Cùng bạn bè tham gia vẽ theo và đoán theo từ khóa. Xem ai có nhanh và vẽ đẹp nhất nhé!",
      "en": "Join friends to draw and guess keywords. See who is the fastest and best at drawing!"
    },
    "players": "2-10",
    "iconPath": "/game/Draw/Img/logo.png",
    "id": "Draw",
    "category": {
      "vi": "Vẽ, Đoán chữ",
      "en": "Draw, Word Guess"
    }
  },
  {
    "name": {
      "vi": "Cờ caro",
      "en": "TicTacToe"
    },
    "desc": {
      "vi": "Trò chơi cờ caro truyền thống, thử thách trí tuệ và chiến lược của bạn!",
      "en": "Traditional TicTacToe game, challenge your intellect and strategy!"
    },
    "players": "2",
    "iconPath": "/game/TicTacToe/Img/logo.png",
    "id": "TicTacToe",
    "category": {
      "vi": "Trí tuệ, Chiến lược",
      "en": "Intellect, Strategy"
    }
  },
  {
    "name": {
      "vi": "Sự thật hay thử thách",
      "en": "Truth or Dare"
    },
    "desc": {
      "vi": "Những sự thật thầm kín, những thử thách độc đáo. Cùng nhau chia sẻ và khám phá!",
      "en": "Secrets and unique challenges. Share and explore together!"
    },
    "players": "2-10",
    "iconPath": "/game/ToD/Img/logo.png",
    "id": "ToD",
    "category": {
      "vi": "Sự thật hay thử thách, Tương tác trực tiếp",
      "en": "Truth or Dare, Interactive"
    }
  },
  {
    "name": {
      "vi": "Đố vui cắm trại",
      "en": "Trivia Camping"
    },
    "desc": {
      "vi": "Catmi có những câu hỏi đố vui thú vị về chủ đề cắm trại. Thử thách kiến thức và cùng khám phá nhé!",
      "en": "Catmi has interesting trivia questions about camping. Challenge your knowledge and explore together!"
    },
    "players": "2-10",
    "iconPath": "/game/Trivia/Img/logo.png",
    "id": "Trivia",
    "category": {
      "vi": "Đố vui, Tương tác với Catmi",
      "en": "Trivia, Interactive with Catmi"
    }
  }
]